[{"tick": "BDLL", "info": "real", "period": "tri", "valor": 230931.0, "data": "2011-03-31", "index": 0}, {"tick": "BDLL", "info": "real", "period": "tri", "valor": 229335.0, "data": "2011-06-30", "index": 1}, {"tick": "BDLL", "info": "real", "period": "tri", "valor": 188223.0, "data": "2011-09-30", "index": 2}, {"tick": "BDLL", "info": "real", "period": "tri", "valor": 156449.0, "data": "2012-03-31", "index": 3}, {"tick": "BDLL", "info": "real", "period": "tri", "valor": 161052.0, "data": "2012-06-30", "index": 4}, {"tick": "BDLL", "info": "real", "period": "tri", "valor": 130714.0, "data": "2012-09-30", "index": 5}, {"tick": "BDLL", "info": "real", "period": "tri", "valor": 146853.0, "data": "2013-03-31", "index": 6}, {"tick": "BDLL", "info": "real", "period": "tri", "valor": 152304.0, "data": "2013-06-30", "index": 7}, {"tick": "BDLL", "info": "real", "period": "tri", "valor": 138726.0, "data": "2013-09-30", "index": 8}, {"tick": "BDLL", "info": "real", "period": "tri", "valor": 152442.0, "data": "2014-03-31", "index": 9}, {"tick": "BDLL", "info": "real", "period": "tri", "valor": 163341.0, "data": "2014-06-30", "index": 10}, {"tick": "BDLL", "info": "real", "period": "tri", "valor": 171290.0, "data": "2014-09-30", "index": 11}, {"tick": "BDLL", "info": "real", "period": "tri", "valor": 199740.0, "data": "2015-03-31", "index": 12}, {"tick": "BDLL", "info": "real", "period": "tri", "valor": 254219.0, "data": "2015-06-30", "index": 13}, {"tick": "BDLL", "info": "real", "period": "tri", "valor": 245754.0, "data": "2015-09-30", "index": 14}, {"tick": "BDLL", "info": "real", "period": "tri", "valor": 203174.0, "data": "2016-03-31", "index": 15}, {"tick": "BDLL", "info": "real", "period": "tri", "valor": 216169.0, "data": "2016-06-30", "index": 16}, {"tick": "BDLL", "info": "real", "period": "tri", "valor": 215568.0, "data": "2016-09-30", "index": 17}, {"tick": "BDLL", "info": "real", "period": "tri", "valor": 133765.0, "data": "2017-03-31", "index": 18}, {"tick": "BDLL", "info": "real", "period": "tri", "valor": 138677.0, "data": "2017-06-30", "index": 19}, {"tick": "BDLL", "info": "real", "period": "tri", "valor": 130089.0, "data": "2017-09-30", "index": 20}, {"tick": "BDLL", "info": "real", "period": "tri", "valor": 144803.0, "data": "2018-03-31", "index": 21}, {"tick": "BDLL", "info": "real", "period": "tri", "valor": 134065.0, "data": "2018-06-30", "index": 22}, {"tick": "BDLL", "info": "real", "period": "tri", "valor": 135567.0, "data": "2018-09-30", "index": 23}, {"tick": "BDLL", "info": "real", "period": "tri", "valor": 124318.0, "data": "2019-03-31", "index": 24}, {"tick": "BDLL", "info": "real", "period": "tri", "valor": 126237.0, "data": "2019-06-30", "index": 25}, {"tick": "BDLL", "info": "real", "period": "tri", "valor": 130771.0, "data": "2019-09-30", "index": 26}, {"tick": "BDLL", "info": "real", "period": "tri", "valor": 126833.0, "data": "2020-03-31", "index": 27}, {"tick": "BDLL", "info": "real", "period": "tri", "valor": 105805.0, "data": "2020-06-30", "index": 28}, {"tick": "BDLL", "info": "real", "period": "tri", "valor": 113461.0, "data": "2020-09-30", "index": 29}, {"tick": "BDLL", "info": "real", "period": "tri", "valor": 117144.0, "data": "2021-03-31", "index": 30}, {"tick": "BDLL", "info": "real", "period": "tri", "valor": 116101.0, "data": "2021-06-30", "index": 31}, {"tick": "BDLL", "info": "real", "period": "tri", "valor": 104362.0, "data": "2021-09-30", "index": 32}, {"tick": "BDLL", "info": "real", "period": "tri", "valor": 172358.0, "data": "2022-03-31", "index": 33}, {"tick": "BDLL", "info": "real", "period": "tri", "valor": 172222.0, "data": "2022-06-30", "index": 34}, {"tick": "BDLL", "info": "real", "period": "tri", "valor": 282222.0, "data": "2022-09-30", "index": 35}, {"tick": "BDLL", "info": "prev", "period": "tri", "valor": 204245.24, "data": "2022-12-30", "index": 36}, {"tick": "BDLL", "info": "prev", "period": "tri", "valor": 221329.48, "data": "2023-03-30", "index": 37}, {"tick": "BDLL", "info": "prev", "period": "tri", "valor": 240602.59, "data": "2023-06-30", "index": 38}, {"tick": "BDLL", "info": "prev", "period": "tri", "valor": 262168.82, "data": "2023-09-30", "index": 39}]