[{"tick": "BEES", "info": "real", "period": "tri", "valor": 352551.0, "data": "2011-03-31", "index": 0}, {"tick": "BEES", "info": "real", "period": "tri", "valor": 121643.0, "data": "2011-09-30", "index": 1}, {"tick": "BEES", "info": "real", "period": "tri", "valor": 135899.0, "data": "2012-03-31", "index": 2}, {"tick": "BEES", "info": "real", "period": "tri", "valor": 130665.0, "data": "2012-09-30", "index": 3}, {"tick": "BEES", "info": "real", "period": "tri", "valor": 169792.0, "data": "2013-03-31", "index": 4}, {"tick": "BEES", "info": "real", "period": "tri", "valor": 198360.0, "data": "2013-09-30", "index": 5}, {"tick": "BEES", "info": "real", "period": "tri", "valor": 231790.0, "data": "2014-03-31", "index": 6}, {"tick": "BEES", "info": "real", "period": "tri", "valor": 285631.0, "data": "2014-09-30", "index": 7}, {"tick": "BEES", "info": "real", "period": "tri", "valor": 331659.0, "data": "2015-03-31", "index": 8}, {"tick": "BEES", "info": "real", "period": "tri", "valor": 97416.0, "data": "2015-09-30", "index": 9}, {"tick": "BEES", "info": "real", "period": "tri", "valor": 141988.0, "data": "2016-03-31", "index": 10}, {"tick": "BEES", "info": "real", "period": "tri", "valor": 193511.0, "data": "2016-09-30", "index": 11}, {"tick": "BEES", "info": "real", "period": "tri", "valor": 242028.0, "data": "2017-03-31", "index": 12}, {"tick": "BEES", "info": "real", "period": "tri", "valor": 294356.0, "data": "2017-09-30", "index": 13}, {"tick": "BEES", "info": "real", "period": "tri", "valor": 354854.0, "data": "2018-03-31", "index": 14}, {"tick": "BEES", "info": "real", "period": "tri", "valor": 399593.0, "data": "2018-09-30", "index": 15}, {"tick": "BEES", "info": "real", "period": "tri", "valor": 453688.0, "data": "2019-03-31", "index": 16}, {"tick": "BEES", "info": "real", "period": "tri", "valor": 506392.0, "data": "2019-09-30", "index": 17}, {"tick": "BEES", "info": "real", "period": "tri", "valor": 285460.0, "data": "2020-03-31", "index": 18}, {"tick": "BEES", "info": "real", "period": "tri", "valor": 358120.0, "data": "2020-09-30", "index": 19}, {"tick": "BEES", "info": "real", "period": "tri", "valor": 450434.0, "data": "2021-03-31", "index": 20}, {"tick": "BEES", "info": "real", "period": "tri", "valor": 504469.0, "data": "2021-09-30", "index": 21}, {"tick": "BEES", "info": "real", "period": "tri", "valor": 288121.0, "data": "2022-03-31", "index": 22}, {"tick": "BEES", "info": "real", "period": "tri", "valor": 350300.0, "data": "2022-09-30", "index": 23}, {"tick": "BEES", "info": "prev", "period": "tri", "valor": 326963.13, "data": "2022-12-30", "index": 24}, {"tick": "BEES", "info": "prev", "period": "tri", "valor": 294992.64, "data": "2023-03-30", "index": 25}, {"tick": "BEES", "info": "prev", "period": "tri", "valor": 257538.21, "data": "2023-06-30", "index": 26}, {"tick": "BEES", "info": "prev", "period": "tri", "valor": 214313.88, "data": "2023-09-30", "index": 27}]