[{"tick": "DMVF", "info": "real", "period": "tri", "valor": -6287.0, "data": "2020-03-31", "index": 0}, {"tick": "DMVF", "info": "real", "period": "tri", "valor": -13031.0, "data": "2020-06-30", "index": 1}, {"tick": "DMVF", "info": "real", "period": "tri", "valor": 1306.0, "data": "2020-09-30", "index": 2}, {"tick": "DMVF", "info": "real", "period": "tri", "valor": -8716.0, "data": "2021-03-31", "index": 3}, {"tick": "DMVF", "info": "real", "period": "tri", "valor": -3308.0, "data": "2021-06-30", "index": 4}, {"tick": "DMVF", "info": "real", "period": "tri", "valor": -2005.0, "data": "2021-09-30", "index": 5}, {"tick": "DMVF", "info": "real", "period": "tri", "valor": -7710.0, "data": "2022-03-31", "index": 6}, {"tick": "DMVF", "info": "real", "period": "tri", "valor": 11745.0, "data": "2022-06-30", "index": 7}, {"tick": "DMVF", "info": "real", "period": "tri", "valor": 3037.0, "data": "2022-09-30", "index": 8}, {"tick": "DMVF", "info": "prev", "period": "tri", "valor": 10318.44, "data": "2022-12-30", "index": 9}, {"tick": "DMVF", "info": "prev", "period": "tri", "valor": 15294.44, "data": "2023-03-30", "index": 10}, {"tick": "DMVF", "info": "prev", "period": "tri", "valor": 21124.19, "data": "2023-06-30", "index": 11}, {"tick": "DMVF", "info": "prev", "period": "tri", "valor": 27877.94, "data": "2023-09-30", "index": 12}]