[{"tick": "ENEV", "info": "real", "period": "tri", "valor": 2008189.0, "data": "2011-03-31", "index": 0}, {"tick": "ENEV", "info": "real", "period": "tri", "valor": 2089153.0, "data": "2011-06-30", "index": 1}, {"tick": "ENEV", "info": "real", "period": "tri", "valor": 3149933.0, "data": "2011-09-30", "index": 2}, {"tick": "ENEV", "info": "real", "period": "tri", "valor": 2903923.0, "data": "2012-03-31", "index": 3}, {"tick": "ENEV", "info": "real", "period": "tri", "valor": 2702683.0, "data": "2012-06-30", "index": 4}, {"tick": "ENEV", "info": "real", "period": "tri", "valor": 3333670.0, "data": "2012-09-30", "index": 5}, {"tick": "ENEV", "info": "real", "period": "tri", "valor": 3878444.0, "data": "2013-03-31", "index": 6}, {"tick": "ENEV", "info": "real", "period": "tri", "valor": 3787710.0, "data": "2013-06-30", "index": 7}, {"tick": "ENEV", "info": "real", "period": "tri", "valor": 4331717.0, "data": "2013-09-30", "index": 8}, {"tick": "ENEV", "info": "real", "period": "tri", "valor": 4600013.0, "data": "2014-03-31", "index": 9}, {"tick": "ENEV", "info": "real", "period": "tri", "valor": 4736905.0, "data": "2014-06-30", "index": 10}, {"tick": "ENEV", "info": "real", "period": "tri", "valor": 4825560.0, "data": "2014-09-30", "index": 11}, {"tick": "ENEV", "info": "real", "period": "tri", "valor": 3661904.0, "data": "2015-03-31", "index": 12}, {"tick": "ENEV", "info": "real", "period": "tri", "valor": 3550068.0, "data": "2015-06-30", "index": 13}, {"tick": "ENEV", "info": "real", "period": "tri", "valor": 3423875.0, "data": "2015-09-30", "index": 14}, {"tick": "ENEV", "info": "real", "period": "tri", "valor": 4707272.0, "data": "2016-03-31", "index": 15}, {"tick": "ENEV", "info": "real", "period": "tri", "valor": 4635487.0, "data": "2016-06-30", "index": 16}, {"tick": "ENEV", "info": "real", "period": "tri", "valor": 4675582.0, "data": "2016-09-30", "index": 17}, {"tick": "ENEV", "info": "real", "period": "tri", "valor": 6063184.0, "data": "2017-03-31", "index": 18}, {"tick": "ENEV", "info": "real", "period": "tri", "valor": 6083848.0, "data": "2017-06-30", "index": 19}, {"tick": "ENEV", "info": "real", "period": "tri", "valor": 6167538.0, "data": "2017-09-30", "index": 20}, {"tick": "ENEV", "info": "real", "period": "tri", "valor": 7108304.0, "data": "2018-03-31", "index": 21}, {"tick": "ENEV", "info": "real", "period": "tri", "valor": 7478685.0, "data": "2018-06-30", "index": 22}, {"tick": "ENEV", "info": "real", "period": "tri", "valor": 7688655.0, "data": "2018-09-30", "index": 23}, {"tick": "ENEV", "info": "real", "period": "tri", "valor": 8394166.0, "data": "2019-03-31", "index": 24}, {"tick": "ENEV", "info": "real", "period": "tri", "valor": 8845608.0, "data": "2019-06-30", "index": 25}, {"tick": "ENEV", "info": "real", "period": "tri", "valor": 9033510.0, "data": "2019-09-30", "index": 26}, {"tick": "ENEV", "info": "real", "period": "tri", "valor": 10333195.0, "data": "2020-03-31", "index": 27}, {"tick": "ENEV", "info": "real", "period": "tri", "valor": 11493797.0, "data": "2020-06-30", "index": 28}, {"tick": "ENEV", "info": "real", "period": "tri", "valor": 12413273.0, "data": "2020-09-30", "index": 29}, {"tick": "ENEV", "info": "real", "period": "tri", "valor": 12877452.0, "data": "2021-03-31", "index": 30}, {"tick": "ENEV", "info": "real", "period": "tri", "valor": 13144400.0, "data": "2021-06-30", "index": 31}, {"tick": "ENEV", "info": "real", "period": "tri", "valor": 13731878.0, "data": "2021-09-30", "index": 32}, {"tick": "ENEV", "info": "real", "period": "tri", "valor": 16302403.0, "data": "2022-03-31", "index": 33}, {"tick": "ENEV", "info": "real", "period": "tri", "valor": 20651923.0, "data": "2022-06-30", "index": 34}, {"tick": "ENEV", "info": "real", "period": "tri", "valor": 25357271.0, "data": "2022-09-30", "index": 35}, {"tick": "ENEV", "info": "prev", "period": "tri", "valor": -24185259.75, "data": "2022-12-30", "index": 36}, {"tick": "ENEV", "info": "prev", "period": "tri", "valor": -26552131.75, "data": "2023-03-30", "index": 37}, {"tick": "ENEV", "info": "prev", "period": "tri", "valor": -29106908.91, "data": "2023-06-30", "index": 38}, {"tick": "ENEV", "info": "prev", "period": "tri", "valor": -31856999.4, "data": "2023-09-30", "index": 39}]