[{"tick": "IRBR", "info": "real", "period": "tri", "valor": 3091059.0, "data": "2017-03-31", "index": 0}, {"tick": "IRBR", "info": "real", "period": "tri", "valor": 3271516.0, "data": "2017-06-30", "index": 1}, {"tick": "IRBR", "info": "real", "period": "tri", "valor": 3439168.0, "data": "2017-09-30", "index": 2}, {"tick": "IRBR", "info": "real", "period": "tri", "valor": 3338759.0, "data": "2018-03-31", "index": 3}, {"tick": "IRBR", "info": "real", "period": "tri", "valor": 3521256.0, "data": "2018-06-30", "index": 4}, {"tick": "IRBR", "info": "real", "period": "tri", "valor": 3762166.0, "data": "2018-09-30", "index": 5}, {"tick": "IRBR", "info": "real", "period": "tri", "valor": 3661170.0, "data": "2019-03-31", "index": 6}, {"tick": "IRBR", "info": "real", "period": "tri", "valor": 3982188.0, "data": "2019-06-30", "index": 7}, {"tick": "IRBR", "info": "real", "period": "tri", "valor": 4262220.0, "data": "2019-09-30", "index": 8}, {"tick": "IRBR", "info": "real", "period": "tri", "valor": 3560953.0, "data": "2020-03-31", "index": 9}, {"tick": "IRBR", "info": "real", "period": "tri", "valor": 2880315.0, "data": "2020-06-30", "index": 10}, {"tick": "IRBR", "info": "real", "period": "tri", "valor": 4876150.0, "data": "2020-09-30", "index": 11}, {"tick": "IRBR", "info": "real", "period": "tri", "valor": 4395844.0, "data": "2021-03-31", "index": 12}, {"tick": "IRBR", "info": "real", "period": "tri", "valor": 4211778.0, "data": "2021-06-30", "index": 13}, {"tick": "IRBR", "info": "real", "period": "tri", "valor": 4025515.0, "data": "2021-09-30", "index": 14}, {"tick": "IRBR", "info": "real", "period": "tri", "valor": 3693410.0, "data": "2022-03-31", "index": 15}, {"tick": "IRBR", "info": "real", "period": "tri", "valor": 3263451.0, "data": "2022-06-30", "index": 16}, {"tick": "IRBR", "info": "real", "period": "tri", "valor": 4106821.0, "data": "2022-09-30", "index": 17}, {"tick": "IRBR", "info": "prev", "period": "tri", "valor": 3550790.69, "data": "2022-12-30", "index": 18}, {"tick": "IRBR", "info": "prev", "period": "tri", "valor": 3362782.15, "data": "2023-03-30", "index": 19}, {"tick": "IRBR", "info": "prev", "period": "tri", "valor": 3138634.12, "data": "2023-06-30", "index": 20}, {"tick": "IRBR", "info": "prev", "period": "tri", "valor": 2876261.53, "data": "2023-09-30", "index": 21}]