[{"tick": "JFEN", "info": "real", "period": "tri", "valor": 44925.0, "data": "2011-06-30", "index": 0}, {"tick": "JFEN", "info": "real", "period": "tri", "valor": 44387.0, "data": "2011-09-30", "index": 1}, {"tick": "JFEN", "info": "real", "period": "tri", "valor": 95242.0, "data": "2012-03-31", "index": 2}, {"tick": "JFEN", "info": "real", "period": "tri", "valor": 95243.0, "data": "2012-09-30", "index": 3}, {"tick": "JFEN", "info": "real", "period": "tri", "valor": 121750.0, "data": "2013-03-31", "index": 4}, {"tick": "JFEN", "info": "real", "period": "tri", "valor": 7984.0, "data": "2013-09-30", "index": 5}, {"tick": "JFEN", "info": "real", "period": "tri", "valor": 46831.0, "data": "2014-03-31", "index": 6}, {"tick": "JFEN", "info": "real", "period": "tri", "valor": -204562.0, "data": "2015-03-31", "index": 7}, {"tick": "JFEN", "info": "real", "period": "tri", "valor": 0.0, "data": "2022-09-30", "index": 8}, {"tick": "JFEN", "info": "prev", "period": "tri", "valor": 3416.18, "data": "2022-12-30", "index": 9}, {"tick": "JFEN", "info": "prev", "period": "tri", "valor": 2920.64, "data": "2023-03-30", "index": 10}, {"tick": "JFEN", "info": "prev", "period": "tri", "valor": 2050.0, "data": "2023-06-30", "index": 11}, {"tick": "JFEN", "info": "prev", "period": "tri", "valor": 766.45, "data": "2023-09-30", "index": 12}]