[{"tick": "LIPR", "info": "real", "period": "tri", "valor": 1179.0, "data": "2011-03-31", "index": 0}, {"tick": "LIPR", "info": "real", "period": "tri", "valor": 14269.0, "data": "2011-06-30", "index": 1}, {"tick": "LIPR", "info": "real", "period": "tri", "valor": 9776.0, "data": "2011-09-30", "index": 2}, {"tick": "LIPR", "info": "real", "period": "tri", "valor": 9463.0, "data": "2012-03-31", "index": 3}, {"tick": "LIPR", "info": "real", "period": "tri", "valor": 2209.0, "data": "2012-06-30", "index": 4}, {"tick": "LIPR", "info": "real", "period": "tri", "valor": 2569.0, "data": "2012-09-30", "index": 5}, {"tick": "LIPR", "info": "real", "period": "tri", "valor": 1910.0, "data": "2013-03-31", "index": 6}, {"tick": "LIPR", "info": "real", "period": "tri", "valor": 454.0, "data": "2013-06-30", "index": 7}, {"tick": "LIPR", "info": "real", "period": "tri", "valor": 2635.0, "data": "2013-09-30", "index": 8}, {"tick": "LIPR", "info": "real", "period": "tri", "valor": -9355.0, "data": "2014-03-30", "index": 9}, {"tick": "LIPR", "info": "real", "period": "tri", "valor": -320.0, "data": "2014-06-30", "index": 10}, {"tick": "LIPR", "info": "real", "period": "tri", "valor": 6332.0, "data": "2014-09-30", "index": 11}, {"tick": "LIPR", "info": "real", "period": "tri", "valor": 1430.0, "data": "2015-03-31", "index": 12}, {"tick": "LIPR", "info": "real", "period": "tri", "valor": 775.0, "data": "2015-06-30", "index": 13}, {"tick": "LIPR", "info": "real", "period": "tri", "valor": 2739.0, "data": "2015-09-30", "index": 14}, {"tick": "LIPR", "info": "real", "period": "tri", "valor": 1403.0, "data": "2016-03-31", "index": 15}, {"tick": "LIPR", "info": "real", "period": "tri", "valor": 1985.0, "data": "2016-06-30", "index": 16}, {"tick": "LIPR", "info": "real", "period": "tri", "valor": 30367.0, "data": "2016-09-30", "index": 17}, {"tick": "LIPR", "info": "real", "period": "tri", "valor": 2416.0, "data": "2017-03-31", "index": 18}, {"tick": "LIPR", "info": "real", "period": "tri", "valor": 2835.0, "data": "2017-06-30", "index": 19}, {"tick": "LIPR", "info": "real", "period": "tri", "valor": 3184.0, "data": "2017-09-30", "index": 20}, {"tick": "LIPR", "info": "real", "period": "tri", "valor": -4560.0, "data": "2018-03-31", "index": 21}, {"tick": "LIPR", "info": "real", "period": "tri", "valor": 4648.0, "data": "2018-06-30", "index": 22}, {"tick": "LIPR", "info": "real", "period": "tri", "valor": 7232.0, "data": "2018-09-30", "index": 23}, {"tick": "LIPR", "info": "real", "period": "tri", "valor": -2957.0, "data": "2019-03-31", "index": 24}, {"tick": "LIPR", "info": "real", "period": "tri", "valor": -405.0, "data": "2019-06-30", "index": 25}, {"tick": "LIPR", "info": "real", "period": "tri", "valor": 2092.0, "data": "2019-09-30", "index": 26}, {"tick": "LIPR", "info": "real", "period": "tri", "valor": 25937.0, "data": "2020-03-31", "index": 27}, {"tick": "LIPR", "info": "real", "period": "tri", "valor": 5277.0, "data": "2020-06-30", "index": 28}, {"tick": "LIPR", "info": "real", "period": "tri", "valor": 2527.0, "data": "2020-09-30", "index": 29}, {"tick": "LIPR", "info": "real", "period": "tri", "valor": 4168.0, "data": "2021-03-31", "index": 30}, {"tick": "LIPR", "info": "real", "period": "tri", "valor": 7598.0, "data": "2021-06-30", "index": 31}, {"tick": "LIPR", "info": "real", "period": "tri", "valor": 2310.0, "data": "2021-09-30", "index": 32}, {"tick": "LIPR", "info": "real", "period": "tri", "valor": 7772.0, "data": "2022-03-31", "index": 33}, {"tick": "LIPR", "info": "real", "period": "tri", "valor": 6397.0, "data": "2022-06-30", "index": 34}, {"tick": "LIPR", "info": "real", "period": "tri", "valor": 4656.0, "data": "2022-09-30", "index": 35}, {"tick": "LIPR", "info": "prev", "period": "tri", "valor": 3870.56, "data": "2022-12-30", "index": 36}, {"tick": "LIPR", "info": "prev", "period": "tri", "valor": 3012.86, "data": "2023-03-30", "index": 37}, {"tick": "LIPR", "info": "prev", "period": "tri", "valor": 2004.84, "data": "2023-06-30", "index": 38}, {"tick": "LIPR", "info": "prev", "period": "tri", "valor": 837.78, "data": "2023-09-30", "index": 39}]