[{"tick": "LLIS", "info": "real", "period": "tri", "valor": 31448.0, "data": "2011-03-31", "index": 0}, {"tick": "LLIS", "info": "real", "period": "tri", "valor": 24945.0, "data": "2011-06-30", "index": 1}, {"tick": "LLIS", "info": "real", "period": "tri", "valor": 6636.0, "data": "2011-09-30", "index": 2}, {"tick": "LLIS", "info": "real", "period": "tri", "valor": 67768.0, "data": "2012-03-31", "index": 3}, {"tick": "LLIS", "info": "real", "period": "tri", "valor": 46117.0, "data": "2012-06-30", "index": 4}, {"tick": "LLIS", "info": "real", "period": "tri", "valor": 55261.0, "data": "2012-09-30", "index": 5}, {"tick": "LLIS", "info": "real", "period": "tri", "valor": 54288.0, "data": "2013-03-31", "index": 6}, {"tick": "LLIS", "info": "real", "period": "tri", "valor": 33461.0, "data": "2013-06-30", "index": 7}, {"tick": "LLIS", "info": "real", "period": "tri", "valor": 20303.0, "data": "2013-09-30", "index": 8}, {"tick": "LLIS", "info": "real", "period": "tri", "valor": 2585.0, "data": "2014-03-31", "index": 9}, {"tick": "LLIS", "info": "real", "period": "tri", "valor": -3539.0, "data": "2014-06-30", "index": 10}, {"tick": "LLIS", "info": "real", "period": "tri", "valor": -9074.0, "data": "2014-09-30", "index": 11}, {"tick": "LLIS", "info": "real", "period": "tri", "valor": -137018.0, "data": "2015-03-31", "index": 12}, {"tick": "LLIS", "info": "real", "period": "tri", "valor": -184661.0, "data": "2015-06-30", "index": 13}, {"tick": "LLIS", "info": "real", "period": "tri", "valor": -185319.0, "data": "2016-09-30", "index": 14}, {"tick": "LLIS", "info": "real", "period": "tri", "valor": 534446.0, "data": "2018-09-30", "index": 15}, {"tick": "LLIS", "info": "real", "period": "tri", "valor": 613337.0, "data": "2019-09-30", "index": 16}, {"tick": "LLIS", "info": "real", "period": "tri", "valor": 420341.0, "data": "2020-09-30", "index": 17}, {"tick": "LLIS", "info": "real", "period": "tri", "valor": 0.0, "data": "2022-09-30", "index": 18}, {"tick": "LLIS", "info": "prev", "period": "tri", "valor": -273463.6, "data": "2022-12-30", "index": 19}, {"tick": "LLIS", "info": "prev", "period": "tri", "valor": -428793.79, "data": "2023-03-30", "index": 20}, {"tick": "LLIS", "info": "prev", "period": "tri", "valor": -604772.75, "data": "2023-06-30", "index": 21}, {"tick": "LLIS", "info": "prev", "period": "tri", "valor": -802428.55, "data": "2023-09-30", "index": 22}]