[{"tick": "MDIA", "info": "real", "period": "tri", "valor": 30608.0, "data": "2011-03-31", "index": 0}, {"tick": "MDIA", "info": "real", "period": "tri", "valor": 40210.0, "data": "2011-06-30", "index": 1}, {"tick": "MDIA", "info": "real", "period": "tri", "valor": 45427.0, "data": "2011-09-30", "index": 2}, {"tick": "MDIA", "info": "real", "period": "tri", "valor": 50882.0, "data": "2012-03-31", "index": 3}, {"tick": "MDIA", "info": "real", "period": "tri", "valor": 65849.0, "data": "2012-06-30", "index": 4}, {"tick": "MDIA", "info": "real", "period": "tri", "valor": 84389.0, "data": "2012-09-30", "index": 5}, {"tick": "MDIA", "info": "real", "period": "tri", "valor": 58420.0, "data": "2013-03-31", "index": 6}, {"tick": "MDIA", "info": "real", "period": "tri", "valor": 71342.0, "data": "2013-06-30", "index": 7}, {"tick": "MDIA", "info": "real", "period": "tri", "valor": 77743.0, "data": "2013-09-30", "index": 8}, {"tick": "MDIA", "info": "real", "period": "tri", "valor": 83679.0, "data": "2014-03-31", "index": 9}, {"tick": "MDIA", "info": "real", "period": "tri", "valor": 108178.0, "data": "2014-06-30", "index": 10}, {"tick": "MDIA", "info": "real", "period": "tri", "valor": 116404.0, "data": "2014-09-30", "index": 11}, {"tick": "MDIA", "info": "real", "period": "tri", "valor": 87952.0, "data": "2015-03-31", "index": 12}, {"tick": "MDIA", "info": "real", "period": "tri", "valor": 129411.0, "data": "2015-06-30", "index": 13}, {"tick": "MDIA", "info": "real", "period": "tri", "valor": 123265.0, "data": "2015-09-30", "index": 14}, {"tick": "MDIA", "info": "real", "period": "tri", "valor": 107564.0, "data": "2016-03-31", "index": 15}, {"tick": "MDIA", "info": "real", "period": "tri", "valor": 141286.0, "data": "2016-06-30", "index": 16}, {"tick": "MDIA", "info": "real", "period": "tri", "valor": 149678.0, "data": "2016-09-30", "index": 17}, {"tick": "MDIA", "info": "real", "period": "tri", "valor": 115682.0, "data": "2017-03-31", "index": 18}, {"tick": "MDIA", "info": "real", "period": "tri", "valor": 152037.0, "data": "2017-06-30", "index": 19}, {"tick": "MDIA", "info": "real", "period": "tri", "valor": 158194.0, "data": "2017-09-30", "index": 20}, {"tick": "MDIA", "info": "real", "period": "tri", "valor": 118650.0, "data": "2018-03-31", "index": 21}, {"tick": "MDIA", "info": "real", "period": "tri", "valor": 157731.0, "data": "2018-06-30", "index": 22}, {"tick": "MDIA", "info": "real", "period": "tri", "valor": 164931.0, "data": "2018-09-30", "index": 23}, {"tick": "MDIA", "info": "real", "period": "tri", "valor": 118631.0, "data": "2019-03-31", "index": 24}, {"tick": "MDIA", "info": "real", "period": "tri", "valor": 155687.0, "data": "2019-06-30", "index": 25}, {"tick": "MDIA", "info": "real", "period": "tri", "valor": 155252.0, "data": "2019-09-30", "index": 26}, {"tick": "MDIA", "info": "real", "period": "tri", "valor": 151123.0, "data": "2020-03-31", "index": 27}, {"tick": "MDIA", "info": "real", "period": "tri", "valor": 245756.0, "data": "2020-06-30", "index": 28}, {"tick": "MDIA", "info": "real", "period": "tri", "valor": 238239.0, "data": "2020-09-30", "index": 29}, {"tick": "MDIA", "info": "real", "period": "tri", "valor": 148276.0, "data": "2021-03-31", "index": 30}, {"tick": "MDIA", "info": "real", "period": "tri", "valor": 190573.0, "data": "2021-06-30", "index": 31}, {"tick": "MDIA", "info": "real", "period": "tri", "valor": 209851.0, "data": "2021-09-30", "index": 32}, {"tick": "MDIA", "info": "real", "period": "tri", "valor": 160544.0, "data": "2022-03-31", "index": 33}, {"tick": "MDIA", "info": "real", "period": "tri", "valor": 212226.0, "data": "2022-06-30", "index": 34}, {"tick": "MDIA", "info": "real", "period": "tri", "valor": 243398.0, "data": "2022-09-30", "index": 35}, {"tick": "MDIA", "info": "prev", "period": "tri", "valor": 227950.7, "data": "2022-12-30", "index": 36}, {"tick": "MDIA", "info": "prev", "period": "tri", "valor": 235812.59, "data": "2023-03-30", "index": 37}, {"tick": "MDIA", "info": "prev", "period": "tri", "valor": 244125.89, "data": "2023-06-30", "index": 38}, {"tick": "MDIA", "info": "prev", "period": "tri", "valor": 252916.27, "data": "2023-09-30", "index": 39}]