[{"tick": "MRVE", "info": "real", "period": "tri", "valor": 6099247.0, "data": "2011-03-31", "index": 0}, {"tick": "MRVE", "info": "real", "period": "tri", "valor": 6207360.0, "data": "2011-06-30", "index": 1}, {"tick": "MRVE", "info": "real", "period": "tri", "valor": 7016280.0, "data": "2011-09-30", "index": 2}, {"tick": "MRVE", "info": "real", "period": "tri", "valor": 7694574.0, "data": "2012-03-31", "index": 3}, {"tick": "MRVE", "info": "real", "period": "tri", "valor": 8291015.0, "data": "2012-06-30", "index": 4}, {"tick": "MRVE", "info": "real", "period": "tri", "valor": 8552283.0, "data": "2012-09-30", "index": 5}, {"tick": "MRVE", "info": "real", "period": "tri", "valor": 8317551.0, "data": "2013-03-31", "index": 6}, {"tick": "MRVE", "info": "real", "period": "tri", "valor": 8397837.0, "data": "2013-06-30", "index": 7}, {"tick": "MRVE", "info": "real", "period": "tri", "valor": 8618902.0, "data": "2013-09-30", "index": 8}, {"tick": "MRVE", "info": "real", "period": "tri", "valor": 8288390.0, "data": "2014-03-31", "index": 9}, {"tick": "MRVE", "info": "real", "period": "tri", "valor": 8429953.0, "data": "2014-06-30", "index": 10}, {"tick": "MRVE", "info": "real", "period": "tri", "valor": 8589218.0, "data": "2014-09-30", "index": 11}, {"tick": "MRVE", "info": "real", "period": "tri", "valor": 9247748.0, "data": "2015-03-31", "index": 12}, {"tick": "MRVE", "info": "real", "period": "tri", "valor": 9463489.0, "data": "2015-06-30", "index": 13}, {"tick": "MRVE", "info": "real", "period": "tri", "valor": 9379688.0, "data": "2015-09-30", "index": 14}, {"tick": "MRVE", "info": "real", "period": "tri", "valor": 9907197.0, "data": "2016-03-31", "index": 15}, {"tick": "MRVE", "info": "real", "period": "tri", "valor": 9697467.0, "data": "2016-06-30", "index": 16}, {"tick": "MRVE", "info": "real", "period": "tri", "valor": 9849565.0, "data": "2016-09-30", "index": 17}, {"tick": "MRVE", "info": "real", "period": "tri", "valor": 11158436.0, "data": "2017-03-31", "index": 18}, {"tick": "MRVE", "info": "real", "period": "tri", "valor": 11116350.0, "data": "2017-06-30", "index": 19}, {"tick": "MRVE", "info": "real", "period": "tri", "valor": 12114637.0, "data": "2017-09-30", "index": 20}, {"tick": "MRVE", "info": "real", "period": "tri", "valor": 12351244.0, "data": "2018-03-31", "index": 21}, {"tick": "MRVE", "info": "real", "period": "tri", "valor": 12205716.0, "data": "2018-06-30", "index": 22}, {"tick": "MRVE", "info": "real", "period": "tri", "valor": 12997010.0, "data": "2018-09-30", "index": 23}, {"tick": "MRVE", "info": "real", "period": "tri", "valor": 12113214.0, "data": "2019-03-31", "index": 24}, {"tick": "MRVE", "info": "real", "period": "tri", "valor": 12476711.0, "data": "2019-06-30", "index": 25}, {"tick": "MRVE", "info": "real", "period": "tri", "valor": 12857445.0, "data": "2019-09-30", "index": 26}, {"tick": "MRVE", "info": "real", "period": "tri", "valor": 12919389.0, "data": "2020-03-31", "index": 27}, {"tick": "MRVE", "info": "real", "period": "tri", "valor": 13555316.0, "data": "2020-06-30", "index": 28}, {"tick": "MRVE", "info": "real", "period": "tri", "valor": 13865171.0, "data": "2020-09-30", "index": 29}, {"tick": "MRVE", "info": "real", "period": "tri", "valor": 14147123.0, "data": "2021-03-31", "index": 30}, {"tick": "MRVE", "info": "real", "period": "tri", "valor": 14458361.0, "data": "2021-06-30", "index": 31}, {"tick": "MRVE", "info": "real", "period": "tri", "valor": 14560374.0, "data": "2021-09-30", "index": 32}, {"tick": "MRVE", "info": "real", "period": "tri", "valor": 14933203.0, "data": "2022-03-31", "index": 33}, {"tick": "MRVE", "info": "real", "period": "tri", "valor": 15123384.0, "data": "2022-06-30", "index": 34}, {"tick": "MRVE", "info": "real", "period": "tri", "valor": 15196329.0, "data": "2022-09-30", "index": 35}, {"tick": "MRVE", "info": "prev", "period": "tri", "valor": -15636591.22, "data": "2022-12-30", "index": 36}, {"tick": "MRVE", "info": "prev", "period": "tri", "valor": -15890635.58, "data": "2023-03-30", "index": 37}, {"tick": "MRVE", "info": "prev", "period": "tri", "valor": -16141993.87, "data": "2023-06-30", "index": 38}, {"tick": "MRVE", "info": "prev", "period": "tri", "valor": -16390433.45, "data": "2023-09-30", "index": 39}]