[{"tick": "PARD", "info": "real", "period": "tri", "valor": 752118.0, "data": "2016-03-31", "index": 0}, {"tick": "PARD", "info": "real", "period": "tri", "valor": 786071.0, "data": "2016-06-30", "index": 1}, {"tick": "PARD", "info": "real", "period": "tri", "valor": 788761.0, "data": "2016-09-30", "index": 2}, {"tick": "PARD", "info": "real", "period": "tri", "valor": 1162339.0, "data": "2017-03-31", "index": 3}, {"tick": "PARD", "info": "real", "period": "tri", "valor": 1021922.0, "data": "2017-06-30", "index": 4}, {"tick": "PARD", "info": "real", "period": "tri", "valor": 1054023.0, "data": "2017-09-30", "index": 5}, {"tick": "PARD", "info": "real", "period": "tri", "valor": 1113085.0, "data": "2018-03-31", "index": 6}, {"tick": "PARD", "info": "real", "period": "tri", "valor": 1198638.0, "data": "2018-06-30", "index": 7}, {"tick": "PARD", "info": "real", "period": "tri", "valor": 1210740.0, "data": "2018-09-30", "index": 8}, {"tick": "PARD", "info": "real", "period": "tri", "valor": 1490470.0, "data": "2019-03-31", "index": 9}, {"tick": "PARD", "info": "real", "period": "tri", "valor": 1488140.0, "data": "2019-06-30", "index": 10}, {"tick": "PARD", "info": "real", "period": "tri", "valor": 1519579.0, "data": "2019-09-30", "index": 11}, {"tick": "PARD", "info": "real", "period": "tri", "valor": 1591725.0, "data": "2020-03-31", "index": 12}, {"tick": "PARD", "info": "real", "period": "tri", "valor": 1806112.0, "data": "2020-06-30", "index": 13}, {"tick": "PARD", "info": "real", "period": "tri", "valor": 1883974.0, "data": "2020-09-30", "index": 14}, {"tick": "PARD", "info": "real", "period": "tri", "valor": 1921716.0, "data": "2021-03-31", "index": 15}, {"tick": "PARD", "info": "real", "period": "tri", "valor": 1952830.0, "data": "2021-06-30", "index": 16}, {"tick": "PARD", "info": "real", "period": "tri", "valor": 2017275.0, "data": "2021-09-30", "index": 17}, {"tick": "PARD", "info": "real", "period": "tri", "valor": 2262415.0, "data": "2022-03-31", "index": 18}, {"tick": "PARD", "info": "real", "period": "tri", "valor": 2146416.0, "data": "2022-06-30", "index": 19}, {"tick": "PARD", "info": "real", "period": "tri", "valor": 2260537.0, "data": "2022-09-30", "index": 20}, {"tick": "PARD", "info": "prev", "period": "tri", "valor": -2327289.93, "data": "2022-12-30", "index": 21}, {"tick": "PARD", "info": "prev", "period": "tri", "valor": -2377699.22, "data": "2023-03-30", "index": 22}, {"tick": "PARD", "info": "prev", "period": "tri", "valor": -2420829.54, "data": "2023-06-30", "index": 23}, {"tick": "PARD", "info": "prev", "period": "tri", "valor": -2456013.54, "data": "2023-09-30", "index": 24}]