[{"tick": "PETR", "info": "real", "period": "tri", "valor": 17691292.0, "data": "2011-03-31", "index": 0}, {"tick": "PETR", "info": "real", "period": "tri", "valor": 17772499.0, "data": "2011-06-30", "index": 1}, {"tick": "PETR", "info": "real", "period": "tri", "valor": 19240634.0, "data": "2011-09-30", "index": 2}, {"tick": "PETR", "info": "real", "period": "tri", "valor": 18796878.0, "data": "2012-03-31", "index": 3}, {"tick": "PETR", "info": "real", "period": "tri", "valor": 16433436.0, "data": "2012-06-30", "index": 4}, {"tick": "PETR", "info": "real", "period": "tri", "valor": 15393203.0, "data": "2012-09-30", "index": 5}, {"tick": "PETR", "info": "real", "period": "tri", "valor": 19306451.0, "data": "2013-03-31", "index": 6}, {"tick": "PETR", "info": "real", "period": "tri", "valor": 17034572.0, "data": "2013-06-30", "index": 7}, {"tick": "PETR", "info": "real", "period": "tri", "valor": 16744445.0, "data": "2013-09-30", "index": 8}, {"tick": "PETR", "info": "real", "period": "tri", "valor": 22893740.0, "data": "2014-03-31", "index": 9}, {"tick": "PETR", "info": "real", "period": "tri", "valor": 22916000.0, "data": "2014-06-30", "index": 10}, {"tick": "PETR", "info": "real", "period": "tri", "valor": 24712000.0, "data": "2014-09-30", "index": 11}, {"tick": "PETR", "info": "real", "period": "tri", "valor": 31120000.0, "data": "2015-03-31", "index": 12}, {"tick": "PETR", "info": "real", "period": "tri", "valor": 24966000.0, "data": "2015-06-30", "index": 13}, {"tick": "PETR", "info": "real", "period": "tri", "valor": 26023000.0, "data": "2015-09-30", "index": 14}, {"tick": "PETR", "info": "real", "period": "tri", "valor": 22613000.0, "data": "2016-03-31", "index": 15}, {"tick": "PETR", "info": "real", "period": "tri", "valor": 21533000.0, "data": "2016-06-30", "index": 16}, {"tick": "PETR", "info": "real", "period": "tri", "valor": 20907000.0, "data": "2016-09-30", "index": 17}, {"tick": "PETR", "info": "real", "period": "tri", "valor": 34808000.0, "data": "2017-03-31", "index": 18}, {"tick": "PETR", "info": "real", "period": "tri", "valor": 35494000.0, "data": "2017-06-30", "index": 19}, {"tick": "PETR", "info": "real", "period": "tri", "valor": 41841000.0, "data": "2017-09-30", "index": 20}, {"tick": "PETR", "info": "real", "period": "tri", "valor": 40865000.0, "data": "2018-03-31", "index": 21}, {"tick": "PETR", "info": "real", "period": "tri", "valor": 50846000.0, "data": "2018-06-30", "index": 22}, {"tick": "PETR", "info": "real", "period": "tri", "valor": 55022000.0, "data": "2018-09-30", "index": 23}, {"tick": "PETR", "info": "real", "period": "tri", "valor": 56677000.0, "data": "2019-03-31", "index": 24}, {"tick": "PETR", "info": "real", "period": "tri", "valor": 107069000.0, "data": "2019-06-30", "index": 25}, {"tick": "PETR", "info": "real", "period": "tri", "valor": 87989000.0, "data": "2019-09-30", "index": 26}, {"tick": "PETR", "info": "real", "period": "tri", "valor": 81824000.0, "data": "2020-03-31", "index": 27}, {"tick": "PETR", "info": "real", "period": "tri", "valor": 67018000.0, "data": "2020-06-30", "index": 28}, {"tick": "PETR", "info": "real", "period": "tri", "valor": 65577000.0, "data": "2020-09-30", "index": 29}, {"tick": "PETR", "info": "real", "period": "tri", "valor": 65168000.0, "data": "2021-03-31", "index": 30}, {"tick": "PETR", "info": "real", "period": "tri", "valor": 96462000.0, "data": "2021-06-30", "index": 31}, {"tick": "PETR", "info": "real", "period": "tri", "valor": 99163000.0, "data": "2021-09-30", "index": 32}, {"tick": "PETR", "info": "real", "period": "tri", "valor": 102928000.0, "data": "2022-03-31", "index": 33}, {"tick": "PETR", "info": "real", "period": "tri", "valor": 121789000.0, "data": "2022-06-30", "index": 34}, {"tick": "PETR", "info": "real", "period": "tri", "valor": 86359000.0, "data": "2022-09-30", "index": 35}, {"tick": "PETR", "info": "prev", "period": "tri", "valor": 109787948.5, "data": "2022-12-30", "index": 36}, {"tick": "PETR", "info": "prev", "period": "tri", "valor": 113336129.75, "data": "2023-03-30", "index": 37}, {"tick": "PETR", "info": "prev", "period": "tri", "valor": 116723138.2, "data": "2023-06-30", "index": 38}, {"tick": "PETR", "info": "prev", "period": "tri", "valor": 119931425.45, "data": "2023-09-30", "index": 39}]