[{"tick": "PETZ", "info": "real", "period": "tri", "valor": 1446589.0, "data": "2020-03-31", "index": 0}, {"tick": "PETZ", "info": "real", "period": "tri", "valor": 1490074.0, "data": "2020-06-30", "index": 1}, {"tick": "PETZ", "info": "real", "period": "tri", "valor": 1838714.0, "data": "2020-09-30", "index": 2}, {"tick": "PETZ", "info": "real", "period": "tri", "valor": 1952068.0, "data": "2021-03-31", "index": 3}, {"tick": "PETZ", "info": "real", "period": "tri", "valor": 1934414.0, "data": "2021-06-30", "index": 4}, {"tick": "PETZ", "info": "real", "period": "tri", "valor": 2026591.0, "data": "2021-09-30", "index": 5}, {"tick": "PETZ", "info": "real", "period": "tri", "valor": 3364347.0, "data": "2022-03-31", "index": 6}, {"tick": "PETZ", "info": "real", "period": "tri", "valor": 3415296.0, "data": "2022-06-30", "index": 7}, {"tick": "PETZ", "info": "real", "period": "tri", "valor": 3498472.0, "data": "2022-09-30", "index": 8}, {"tick": "PETZ", "info": "prev", "period": "tri", "valor": -3956513.45, "data": "2022-12-30", "index": 9}, {"tick": "PETZ", "info": "prev", "period": "tri", "valor": -4187213.36, "data": "2023-03-30", "index": 10}, {"tick": "PETZ", "info": "prev", "period": "tri", "valor": -4312483.68, "data": "2023-06-30", "index": 11}, {"tick": "PETZ", "info": "prev", "period": "tri", "valor": -4305788.43, "data": "2023-09-30", "index": 12}]