[{"tick": "PMAM", "info": "real", "period": "tri", "valor": 38024.0, "data": "2011-03-31", "index": 0}, {"tick": "PMAM", "info": "real", "period": "tri", "valor": 42621.0, "data": "2011-06-30", "index": 1}, {"tick": "PMAM", "info": "real", "period": "tri", "valor": 46542.0, "data": "2011-09-30", "index": 2}, {"tick": "PMAM", "info": "real", "period": "tri", "valor": 35228.0, "data": "2012-03-31", "index": 3}, {"tick": "PMAM", "info": "real", "period": "tri", "valor": 44754.0, "data": "2012-06-30", "index": 4}, {"tick": "PMAM", "info": "real", "period": "tri", "valor": 46679.0, "data": "2012-09-30", "index": 5}, {"tick": "PMAM", "info": "real", "period": "tri", "valor": 39960.0, "data": "2013-03-31", "index": 6}, {"tick": "PMAM", "info": "real", "period": "tri", "valor": 47386.0, "data": "2013-06-30", "index": 7}, {"tick": "PMAM", "info": "real", "period": "tri", "valor": 55827.0, "data": "2013-09-30", "index": 8}, {"tick": "PMAM", "info": "real", "period": "tri", "valor": 42083.0, "data": "2014-03-31", "index": 9}, {"tick": "PMAM", "info": "real", "period": "tri", "valor": 36254.0, "data": "2014-06-30", "index": 10}, {"tick": "PMAM", "info": "real", "period": "tri", "valor": 42945.0, "data": "2014-09-30", "index": 11}, {"tick": "PMAM", "info": "real", "period": "tri", "valor": 42706.0, "data": "2015-03-31", "index": 12}, {"tick": "PMAM", "info": "real", "period": "tri", "valor": 36518.0, "data": "2015-06-30", "index": 13}, {"tick": "PMAM", "info": "real", "period": "tri", "valor": 54255.0, "data": "2015-09-30", "index": 14}, {"tick": "PMAM", "info": "real", "period": "tri", "valor": 42480.0, "data": "2016-03-31", "index": 15}, {"tick": "PMAM", "info": "real", "period": "tri", "valor": 44782.0, "data": "2016-06-30", "index": 16}, {"tick": "PMAM", "info": "real", "period": "tri", "valor": 58541.0, "data": "2016-09-30", "index": 17}, {"tick": "PMAM", "info": "real", "period": "tri", "valor": 40733.0, "data": "2017-03-31", "index": 18}, {"tick": "PMAM", "info": "real", "period": "tri", "valor": 43306.0, "data": "2017-06-30", "index": 19}, {"tick": "PMAM", "info": "real", "period": "tri", "valor": 53081.0, "data": "2017-09-30", "index": 20}, {"tick": "PMAM", "info": "real", "period": "tri", "valor": 45818.0, "data": "2018-03-31", "index": 21}, {"tick": "PMAM", "info": "real", "period": "tri", "valor": 49668.0, "data": "2018-06-30", "index": 22}, {"tick": "PMAM", "info": "real", "period": "tri", "valor": 62672.0, "data": "2018-09-30", "index": 23}, {"tick": "PMAM", "info": "real", "period": "tri", "valor": 52875.0, "data": "2019-03-31", "index": 24}, {"tick": "PMAM", "info": "real", "period": "tri", "valor": 57109.0, "data": "2019-06-30", "index": 25}, {"tick": "PMAM", "info": "real", "period": "tri", "valor": 60584.0, "data": "2019-09-30", "index": 26}, {"tick": "PMAM", "info": "real", "period": "tri", "valor": 47085.0, "data": "2020-03-31", "index": 27}, {"tick": "PMAM", "info": "real", "period": "tri", "valor": 57045.0, "data": "2020-06-30", "index": 28}, {"tick": "PMAM", "info": "real", "period": "tri", "valor": 62305.0, "data": "2020-09-30", "index": 29}, {"tick": "PMAM", "info": "real", "period": "tri", "valor": 45786.0, "data": "2021-03-31", "index": 30}, {"tick": "PMAM", "info": "real", "period": "tri", "valor": 45121.0, "data": "2021-06-30", "index": 31}, {"tick": "PMAM", "info": "real", "period": "tri", "valor": 49833.0, "data": "2021-09-30", "index": 32}, {"tick": "PMAM", "info": "real", "period": "tri", "valor": 45232.0, "data": "2022-03-31", "index": 33}, {"tick": "PMAM", "info": "real", "period": "tri", "valor": 45334.0, "data": "2022-06-30", "index": 34}, {"tick": "PMAM", "info": "real", "period": "tri", "valor": 49490.0, "data": "2022-09-30", "index": 35}, {"tick": "PMAM", "info": "prev", "period": "tri", "valor": 43610.7, "data": "2022-12-30", "index": 36}, {"tick": "PMAM", "info": "prev", "period": "tri", "valor": 41325.43, "data": "2023-03-30", "index": 37}, {"tick": "PMAM", "info": "prev", "period": "tri", "valor": 38743.03, "data": "2023-06-30", "index": 38}, {"tick": "PMAM", "info": "prev", "period": "tri", "valor": 35849.84, "data": "2023-09-30", "index": 39}]