[{"tick": "PTBL", "info": "real", "period": "tri", "valor": 118781.0, "data": "2011-03-31", "index": 0}, {"tick": "PTBL", "info": "real", "period": "tri", "valor": 131491.0, "data": "2011-06-30", "index": 1}, {"tick": "PTBL", "info": "real", "period": "tri", "valor": 156537.0, "data": "2011-09-30", "index": 2}, {"tick": "PTBL", "info": "real", "period": "tri", "valor": 139384.0, "data": "2012-03-31", "index": 3}, {"tick": "PTBL", "info": "real", "period": "tri", "valor": 146494.0, "data": "2012-06-30", "index": 4}, {"tick": "PTBL", "info": "real", "period": "tri", "valor": 193629.0, "data": "2012-09-30", "index": 5}, {"tick": "PTBL", "info": "real", "period": "tri", "valor": 164979.0, "data": "2013-03-31", "index": 6}, {"tick": "PTBL", "info": "real", "period": "tri", "valor": 194000.0, "data": "2013-06-30", "index": 7}, {"tick": "PTBL", "info": "real", "period": "tri", "valor": 206937.0, "data": "2013-09-30", "index": 8}, {"tick": "PTBL", "info": "real", "period": "tri", "valor": 191905.0, "data": "2014-03-31", "index": 9}, {"tick": "PTBL", "info": "real", "period": "tri", "valor": 217290.0, "data": "2014-06-30", "index": 10}, {"tick": "PTBL", "info": "real", "period": "tri", "valor": 234295.0, "data": "2014-09-30", "index": 11}, {"tick": "PTBL", "info": "real", "period": "tri", "valor": 223395.0, "data": "2015-03-31", "index": 12}, {"tick": "PTBL", "info": "real", "period": "tri", "valor": 234654.0, "data": "2015-06-30", "index": 13}, {"tick": "PTBL", "info": "real", "period": "tri", "valor": 255454.0, "data": "2015-09-30", "index": 14}, {"tick": "PTBL", "info": "real", "period": "tri", "valor": 221086.0, "data": "2016-03-31", "index": 15}, {"tick": "PTBL", "info": "real", "period": "tri", "valor": 233480.0, "data": "2016-06-30", "index": 16}, {"tick": "PTBL", "info": "real", "period": "tri", "valor": 247942.0, "data": "2016-09-30", "index": 17}, {"tick": "PTBL", "info": "real", "period": "tri", "valor": 213213.0, "data": "2017-03-31", "index": 18}, {"tick": "PTBL", "info": "real", "period": "tri", "valor": 235871.0, "data": "2017-06-30", "index": 19}, {"tick": "PTBL", "info": "real", "period": "tri", "valor": 250482.0, "data": "2017-09-30", "index": 20}, {"tick": "PTBL", "info": "real", "period": "tri", "valor": 223310.0, "data": "2018-03-31", "index": 21}, {"tick": "PTBL", "info": "real", "period": "tri", "valor": 242029.0, "data": "2018-06-30", "index": 22}, {"tick": "PTBL", "info": "real", "period": "tri", "valor": 250837.0, "data": "2018-09-30", "index": 23}, {"tick": "PTBL", "info": "real", "period": "tri", "valor": 214613.0, "data": "2019-03-31", "index": 24}, {"tick": "PTBL", "info": "real", "period": "tri", "valor": 244426.0, "data": "2019-06-30", "index": 25}, {"tick": "PTBL", "info": "real", "period": "tri", "valor": 262200.0, "data": "2019-09-30", "index": 26}, {"tick": "PTBL", "info": "real", "period": "tri", "valor": 239562.0, "data": "2020-03-31", "index": 27}, {"tick": "PTBL", "info": "real", "period": "tri", "valor": 215874.0, "data": "2020-06-30", "index": 28}, {"tick": "PTBL", "info": "real", "period": "tri", "valor": 360022.0, "data": "2020-09-30", "index": 29}, {"tick": "PTBL", "info": "real", "period": "tri", "valor": 347314.0, "data": "2021-03-31", "index": 30}, {"tick": "PTBL", "info": "real", "period": "tri", "valor": 385005.0, "data": "2021-06-30", "index": 31}, {"tick": "PTBL", "info": "real", "period": "tri", "valor": 422606.0, "data": "2021-09-30", "index": 32}, {"tick": "PTBL", "info": "real", "period": "tri", "valor": 428033.0, "data": "2022-03-31", "index": 33}, {"tick": "PTBL", "info": "real", "period": "tri", "valor": 464113.0, "data": "2022-06-30", "index": 34}, {"tick": "PTBL", "info": "real", "period": "tri", "valor": 477806.0, "data": "2022-09-30", "index": 35}, {"tick": "PTBL", "info": "prev", "period": "tri", "valor": 542149.72, "data": "2022-12-30", "index": 36}, {"tick": "PTBL", "info": "prev", "period": "tri", "valor": 590669.38, "data": "2023-03-30", "index": 37}, {"tick": "PTBL", "info": "prev", "period": "tri", "valor": 643867.34, "data": "2023-06-30", "index": 38}, {"tick": "PTBL", "info": "prev", "period": "tri", "valor": 701958.54, "data": "2023-09-30", "index": 39}]