[{"tick": "QUSW", "info": "real", "period": "tri", "valor": 6582479.0, "data": "2013-03-31", "index": 0}, {"tick": "QUSW", "info": "real", "period": "tri", "valor": 7441129.0, "data": "2013-06-30", "index": 1}, {"tick": "QUSW", "info": "real", "period": "tri", "valor": 8434983.0, "data": "2013-09-30", "index": 2}, {"tick": "QUSW", "info": "real", "period": "tri", "valor": 8239455.52, "data": "2014-03-31", "index": 3}, {"tick": "QUSW", "info": "real", "period": "tri", "valor": 9235164.0, "data": "2014-06-30", "index": 4}, {"tick": "QUSW", "info": "real", "period": "tri", "valor": 9883997.0, "data": "2014-09-30", "index": 5}, {"tick": "QUSW", "info": "real", "period": "tri", "valor": 9859628.0, "data": "2015-03-31", "index": 6}, {"tick": "QUSW", "info": "real", "period": "tri", "valor": 10357895.0, "data": "2015-06-30", "index": 7}, {"tick": "QUSW", "info": "real", "period": "tri", "valor": 14510682.0, "data": "2015-09-30", "index": 8}, {"tick": "QUSW", "info": "real", "period": "tri", "valor": 11239402.0, "data": "2016-03-31", "index": 9}, {"tick": "QUSW", "info": "real", "period": "tri", "valor": 10906351.0, "data": "2016-06-30", "index": 10}, {"tick": "QUSW", "info": "real", "period": "tri", "valor": 14053889.0, "data": "2016-09-30", "index": 11}, {"tick": "QUSW", "info": "real", "period": "tri", "valor": 9860554.0, "data": "2017-03-31", "index": 12}, {"tick": "QUSW", "info": "real", "period": "tri", "valor": 11068259.0, "data": "2017-06-30", "index": 13}, {"tick": "QUSW", "info": "real", "period": "tri", "valor": 11604895.0, "data": "2017-09-30", "index": 14}, {"tick": "QUSW", "info": "real", "period": "tri", "valor": 10992578.0, "data": "2018-03-31", "index": 15}, {"tick": "QUSW", "info": "real", "period": "tri", "valor": 11396466.0, "data": "2018-06-30", "index": 16}, {"tick": "QUSW", "info": "real", "period": "tri", "valor": 12238249.0, "data": "2018-09-30", "index": 17}, {"tick": "QUSW", "info": "real", "period": "tri", "valor": 13634055.0, "data": "2019-03-31", "index": 18}, {"tick": "QUSW", "info": "real", "period": "tri", "valor": 15919275.0, "data": "2019-06-30", "index": 19}, {"tick": "QUSW", "info": "real", "period": "tri", "valor": 15480300.0, "data": "2019-09-30", "index": 20}, {"tick": "QUSW", "info": "real", "period": "tri", "valor": 15606180.0, "data": "2020-03-31", "index": 21}, {"tick": "QUSW", "info": "real", "period": "tri", "valor": 13968755.0, "data": "2020-06-30", "index": 22}, {"tick": "QUSW", "info": "real", "period": "tri", "valor": 13957738.0, "data": "2020-09-30", "index": 23}, {"tick": "QUSW", "info": "real", "period": "tri", "valor": 15356579.0, "data": "2021-03-31", "index": 24}, {"tick": "QUSW", "info": "real", "period": "tri", "valor": 15493335.0, "data": "2021-06-30", "index": 25}, {"tick": "QUSW", "info": "real", "period": "tri", "valor": 14864854.0, "data": "2021-09-30", "index": 26}, {"tick": "QUSW", "info": "real", "period": "tri", "valor": 14119277.0, "data": "2022-03-31", "index": 27}, {"tick": "QUSW", "info": "real", "period": "tri", "valor": 14487779.0, "data": "2022-06-30", "index": 28}, {"tick": "QUSW", "info": "real", "period": "tri", "valor": 13266843.0, "data": "2022-09-30", "index": 29}, {"tick": "QUSW", "info": "prev", "period": "tri", "valor": 14270073.62, "data": "2022-12-30", "index": 30}, {"tick": "QUSW", "info": "prev", "period": "tri", "valor": 14117334.33, "data": "2023-03-30", "index": 31}, {"tick": "QUSW", "info": "prev", "period": "tri", "valor": 13929110.58, "data": "2023-06-30", "index": 32}, {"tick": "QUSW", "info": "prev", "period": "tri", "valor": 13704401.94, "data": "2023-09-30", "index": 33}]