[{"tick": "RSUL", "info": "real", "period": "tri", "valor": 14179.0, "data": "2011-03-31", "index": 0}, {"tick": "RSUL", "info": "real", "period": "tri", "valor": 16426.0, "data": "2011-06-30", "index": 1}, {"tick": "RSUL", "info": "real", "period": "tri", "valor": 20533.0, "data": "2011-09-30", "index": 2}, {"tick": "RSUL", "info": "real", "period": "tri", "valor": 23350.0, "data": "2012-03-31", "index": 3}, {"tick": "RSUL", "info": "real", "period": "tri", "valor": 29354.0, "data": "2012-06-30", "index": 4}, {"tick": "RSUL", "info": "real", "period": "tri", "valor": 32539.0, "data": "2012-09-30", "index": 5}, {"tick": "RSUL", "info": "real", "period": "tri", "valor": 39067.0, "data": "2013-03-31", "index": 6}, {"tick": "RSUL", "info": "real", "period": "tri", "valor": 43350.0, "data": "2013-06-30", "index": 7}, {"tick": "RSUL", "info": "real", "period": "tri", "valor": 46506.0, "data": "2013-09-30", "index": 8}, {"tick": "RSUL", "info": "real", "period": "tri", "valor": 50695.0, "data": "2014-03-31", "index": 9}, {"tick": "RSUL", "info": "real", "period": "tri", "valor": 53436.0, "data": "2014-06-30", "index": 10}, {"tick": "RSUL", "info": "real", "period": "tri", "valor": 17330.0, "data": "2014-09-30", "index": 11}, {"tick": "RSUL", "info": "real", "period": "tri", "valor": 22727.0, "data": "2015-03-31", "index": 12}, {"tick": "RSUL", "info": "real", "period": "tri", "valor": 27609.0, "data": "2015-06-30", "index": 13}, {"tick": "RSUL", "info": "real", "period": "tri", "valor": 31450.0, "data": "2015-09-30", "index": 14}, {"tick": "RSUL", "info": "real", "period": "tri", "valor": 39156.0, "data": "2016-03-31", "index": 15}, {"tick": "RSUL", "info": "real", "period": "tri", "valor": 42058.0, "data": "2016-06-30", "index": 16}, {"tick": "RSUL", "info": "real", "period": "tri", "valor": 45215.0, "data": "2016-09-30", "index": 17}, {"tick": "RSUL", "info": "real", "period": "tri", "valor": 52869.0, "data": "2017-03-31", "index": 18}, {"tick": "RSUL", "info": "real", "period": "tri", "valor": 54629.0, "data": "2017-06-30", "index": 19}, {"tick": "RSUL", "info": "real", "period": "tri", "valor": 45970.0, "data": "2017-09-30", "index": 20}, {"tick": "RSUL", "info": "real", "period": "tri", "valor": 35121.0, "data": "2018-03-31", "index": 21}, {"tick": "RSUL", "info": "real", "period": "tri", "valor": 36009.0, "data": "2018-06-30", "index": 22}, {"tick": "RSUL", "info": "real", "period": "tri", "valor": 36357.0, "data": "2018-09-30", "index": 23}, {"tick": "RSUL", "info": "real", "period": "tri", "valor": 35767.0, "data": "2019-03-31", "index": 24}, {"tick": "RSUL", "info": "real", "period": "tri", "valor": 37217.0, "data": "2019-06-30", "index": 25}, {"tick": "RSUL", "info": "real", "period": "tri", "valor": 35415.0, "data": "2019-09-30", "index": 26}, {"tick": "RSUL", "info": "real", "period": "tri", "valor": 32762.0, "data": "2020-03-31", "index": 27}, {"tick": "RSUL", "info": "real", "period": "tri", "valor": 32017.0, "data": "2020-06-30", "index": 28}, {"tick": "RSUL", "info": "real", "period": "tri", "valor": 32423.0, "data": "2020-09-30", "index": 29}, {"tick": "RSUL", "info": "real", "period": "tri", "valor": 11956.0, "data": "2021-03-31", "index": 30}, {"tick": "RSUL", "info": "real", "period": "tri", "valor": 13784.0, "data": "2021-06-30", "index": 31}, {"tick": "RSUL", "info": "real", "period": "tri", "valor": 15837.0, "data": "2021-09-30", "index": 32}, {"tick": "RSUL", "info": "real", "period": "tri", "valor": 17007.0, "data": "2022-03-31", "index": 33}, {"tick": "RSUL", "info": "real", "period": "tri", "valor": 19820.0, "data": "2022-06-30", "index": 34}, {"tick": "RSUL", "info": "real", "period": "tri", "valor": 20871.0, "data": "2022-09-30", "index": 35}, {"tick": "RSUL", "info": "prev", "period": "tri", "valor": 11943.75, "data": "2022-12-30", "index": 36}, {"tick": "RSUL", "info": "prev", "period": "tri", "valor": 9669.52, "data": "2023-03-30", "index": 37}, {"tick": "RSUL", "info": "prev", "period": "tri", "valor": 7385.49, "data": "2023-06-30", "index": 38}, {"tick": "RSUL", "info": "prev", "period": "tri", "valor": 5100.18, "data": "2023-09-30", "index": 39}]