[{"tick": "VIVR", "info": "real", "period": "tri", "valor": 1129056.0, "data": "2011-03-31", "index": 0}, {"tick": "VIVR", "info": "real", "period": "tri", "valor": 1139359.0, "data": "2011-06-30", "index": 1}, {"tick": "VIVR", "info": "real", "period": "tri", "valor": 1126660.0, "data": "2011-09-30", "index": 2}, {"tick": "VIVR", "info": "real", "period": "tri", "valor": 984073.0, "data": "2012-03-31", "index": 3}, {"tick": "VIVR", "info": "real", "period": "tri", "valor": 938344.0, "data": "2012-06-30", "index": 4}, {"tick": "VIVR", "info": "real", "period": "tri", "valor": 752687.0, "data": "2012-09-30", "index": 5}, {"tick": "VIVR", "info": "real", "period": "tri", "valor": 549546.0, "data": "2013-03-31", "index": 6}, {"tick": "VIVR", "info": "real", "period": "tri", "valor": 503402.0, "data": "2013-06-30", "index": 7}, {"tick": "VIVR", "info": "real", "period": "tri", "valor": 430386.0, "data": "2013-09-30", "index": 8}, {"tick": "VIVR", "info": "real", "period": "tri", "valor": 273121.0, "data": "2014-03-31", "index": 9}, {"tick": "VIVR", "info": "real", "period": "tri", "valor": 168162.0, "data": "2014-06-30", "index": 10}, {"tick": "VIVR", "info": "real", "period": "tri", "valor": 139553.0, "data": "2014-09-30", "index": 11}, {"tick": "VIVR", "info": "real", "period": "tri", "valor": 31126.0, "data": "2015-03-31", "index": 12}, {"tick": "VIVR", "info": "real", "period": "tri", "valor": -36444.0, "data": "2015-06-30", "index": 13}, {"tick": "VIVR", "info": "real", "period": "tri", "valor": -93305.0, "data": "2015-09-30", "index": 14}, {"tick": "VIVR", "info": "real", "period": "tri", "valor": -274053.0, "data": "2016-03-31", "index": 15}, {"tick": "VIVR", "info": "real", "period": "tri", "valor": -348091.0, "data": "2016-06-30", "index": 16}, {"tick": "VIVR", "info": "real", "period": "tri", "valor": -428732.0, "data": "2016-09-30", "index": 17}, {"tick": "VIVR", "info": "real", "period": "tri", "valor": -537930.0, "data": "2017-03-31", "index": 18}, {"tick": "VIVR", "info": "real", "period": "tri", "valor": -623559.0, "data": "2017-06-30", "index": 19}, {"tick": "VIVR", "info": "real", "period": "tri", "valor": -605738.0, "data": "2017-09-30", "index": 20}, {"tick": "VIVR", "info": "real", "period": "tri", "valor": -84622.0, "data": "2018-03-31", "index": 21}, {"tick": "VIVR", "info": "real", "period": "tri", "valor": -104892.0, "data": "2018-06-30", "index": 22}, {"tick": "VIVR", "info": "real", "period": "tri", "valor": -176874.0, "data": "2018-09-30", "index": 23}, {"tick": "VIVR", "info": "real", "period": "tri", "valor": 66512.0, "data": "2019-03-31", "index": 24}, {"tick": "VIVR", "info": "real", "period": "tri", "valor": -12568.0, "data": "2019-06-30", "index": 25}, {"tick": "VIVR", "info": "real", "period": "tri", "valor": -92585.0, "data": "2019-09-30", "index": 26}, {"tick": "VIVR", "info": "real", "period": "tri", "valor": -144472.0, "data": "2020-03-31", "index": 27}, {"tick": "VIVR", "info": "real", "period": "tri", "valor": -154240.0, "data": "2020-06-30", "index": 28}, {"tick": "VIVR", "info": "real", "period": "tri", "valor": -182109.0, "data": "2020-09-30", "index": 29}, {"tick": "VIVR", "info": "real", "period": "tri", "valor": -227027.0, "data": "2021-03-31", "index": 30}, {"tick": "VIVR", "info": "real", "period": "tri", "valor": -170146.0, "data": "2021-06-30", "index": 31}, {"tick": "VIVR", "info": "real", "period": "tri", "valor": -180814.0, "data": "2021-09-30", "index": 32}, {"tick": "VIVR", "info": "real", "period": "tri", "valor": -209496.0, "data": "2022-03-31", "index": 33}, {"tick": "VIVR", "info": "real", "period": "tri", "valor": -191558.0, "data": "2022-06-30", "index": 34}, {"tick": "VIVR", "info": "real", "period": "tri", "valor": -174609.0, "data": "2022-09-30", "index": 35}, {"tick": "VIVR", "info": "prev", "period": "tri", "valor": -113766.4, "data": "2022-12-30", "index": 36}, {"tick": "VIVR", "info": "prev", "period": "tri", "valor": -108943.21, "data": "2023-03-30", "index": 37}, {"tick": "VIVR", "info": "prev", "period": "tri", "valor": -107280.61, "data": "2023-06-30", "index": 38}, {"tick": "VIVR", "info": "prev", "period": "tri", "valor": -109230.27, "data": "2023-09-30", "index": 39}]