[{"tick": "WLMM", "info": "real", "period": "tri", "valor": 4798.0, "data": "2011-03-31", "index": 0}, {"tick": "WLMM", "info": "real", "period": "tri", "valor": 6369.0, "data": "2011-06-30", "index": 1}, {"tick": "WLMM", "info": "real", "period": "tri", "valor": 6127.0, "data": "2011-09-30", "index": 2}, {"tick": "WLMM", "info": "real", "period": "tri", "valor": -4803.0, "data": "2012-03-31", "index": 3}, {"tick": "WLMM", "info": "real", "period": "tri", "valor": -1825.0, "data": "2012-06-30", "index": 4}, {"tick": "WLMM", "info": "real", "period": "tri", "valor": -439.0, "data": "2012-09-30", "index": 5}, {"tick": "WLMM", "info": "real", "period": "tri", "valor": 1863.0, "data": "2013-03-31", "index": 6}, {"tick": "WLMM", "info": "real", "period": "tri", "valor": 794.0, "data": "2013-06-30", "index": 7}, {"tick": "WLMM", "info": "real", "period": "tri", "valor": 6928.0, "data": "2013-09-30", "index": 8}, {"tick": "WLMM", "info": "real", "period": "tri", "valor": 5719.0, "data": "2014-03-31", "index": 9}, {"tick": "WLMM", "info": "real", "period": "tri", "valor": -1405.0, "data": "2014-06-30", "index": 10}, {"tick": "WLMM", "info": "real", "period": "tri", "valor": 6301.0, "data": "2014-09-30", "index": 11}, {"tick": "WLMM", "info": "real", "period": "tri", "valor": -3924.0, "data": "2015-03-31", "index": 12}, {"tick": "WLMM", "info": "real", "period": "tri", "valor": 1876.0, "data": "2015-06-30", "index": 13}, {"tick": "WLMM", "info": "real", "period": "tri", "valor": 144.0, "data": "2015-09-30", "index": 14}, {"tick": "WLMM", "info": "real", "period": "tri", "valor": -4972.0, "data": "2016-03-31", "index": 15}, {"tick": "WLMM", "info": "real", "period": "tri", "valor": -6459.0, "data": "2016-06-30", "index": 16}, {"tick": "WLMM", "info": "real", "period": "tri", "valor": -4813.0, "data": "2016-09-30", "index": 17}, {"tick": "WLMM", "info": "real", "period": "tri", "valor": -1628.0, "data": "2017-03-31", "index": 18}, {"tick": "WLMM", "info": "real", "period": "tri", "valor": -1047.0, "data": "2017-06-30", "index": 19}, {"tick": "WLMM", "info": "real", "period": "tri", "valor": 2083.0, "data": "2017-09-30", "index": 20}, {"tick": "WLMM", "info": "real", "period": "tri", "valor": 3128.0, "data": "2018-03-31", "index": 21}, {"tick": "WLMM", "info": "real", "period": "tri", "valor": -1021.0, "data": "2018-06-30", "index": 22}, {"tick": "WLMM", "info": "real", "period": "tri", "valor": 6682.0, "data": "2018-09-30", "index": 23}, {"tick": "WLMM", "info": "real", "period": "tri", "valor": 6680.0, "data": "2019-03-31", "index": 24}, {"tick": "WLMM", "info": "real", "period": "tri", "valor": 8481.0, "data": "2019-06-30", "index": 25}, {"tick": "WLMM", "info": "real", "period": "tri", "valor": 359229.0, "data": "2019-09-30", "index": 26}, {"tick": "WLMM", "info": "real", "period": "tri", "valor": 198616.0, "data": "2020-03-31", "index": 27}, {"tick": "WLMM", "info": "real", "period": "tri", "valor": 189289.0, "data": "2020-06-30", "index": 28}, {"tick": "WLMM", "info": "real", "period": "tri", "valor": 232014.0, "data": "2020-09-30", "index": 29}, {"tick": "WLMM", "info": "real", "period": "tri", "valor": 439927.0, "data": "2021-03-31", "index": 30}, {"tick": "WLMM", "info": "real", "period": "tri", "valor": 533827.0, "data": "2021-06-30", "index": 31}, {"tick": "WLMM", "info": "real", "period": "tri", "valor": 407044.0, "data": "2021-09-30", "index": 32}, {"tick": "WLMM", "info": "real", "period": "tri", "valor": 213728.0, "data": "2022-03-31", "index": 33}, {"tick": "WLMM", "info": "real", "period": "tri", "valor": 461467.0, "data": "2022-06-30", "index": 34}, {"tick": "WLMM", "info": "real", "period": "tri", "valor": 635980.0, "data": "2022-09-30", "index": 35}, {"tick": "WLMM", "info": "prev", "period": "tri", "valor": 654781.82, "data": "2022-12-30", "index": 36}, {"tick": "WLMM", "info": "prev", "period": "tri", "valor": 732435.78, "data": "2023-03-30", "index": 37}, {"tick": "WLMM", "info": "prev", "period": "tri", "valor": 815702.0, "data": "2023-06-30", "index": 38}, {"tick": "WLMM", "info": "prev", "period": "tri", "valor": 904768.83, "data": "2023-09-30", "index": 39}]